u2p/__init__.py
u2p/__main__.py
u2p/cli.py
u2p/utils.py
u2p/transformers/__init__.py
u2p/transformers/asserts.py
u2p/transformers/main.py
u2p/transformers/generic/__init__.py
u2p/transformers/generic/bases.py
u2p-0.2.0.dist-info/LICENSE
u2p-0.2.0.dist-info/METADATA
u2p-0.2.0.dist-info/WHEEL
u2p-0.2.0.dist-info/entry_points.txt
u2p-0.2.0.dist-info/top_level.txt
u2p-0.2.0.dist-info/RECORD
